is_disposable_email/__init__.py
is_disposable_email/_domains.py
is_disposable_email-1.0.0.dist-info/LICENSE
is_disposable_email-1.0.0.dist-info/METADATA
is_disposable_email-1.0.0.dist-info/WHEEL
is_disposable_email-1.0.0.dist-info/top_level.txt
is_disposable_email-1.0.0.dist-info/RECORD
