Metadata-Version: 2.1
Name: is_disposable_email
Version: 1.0.0
Summary: Check if the email address is from a disposable email service         provider
Home-page: https://github.com/akhilharihar/is_disposable_email
Author: Akhil Harihar
Author-email: hariharakhil@gmail.com
License: UNKNOWN
Platform: UNKNOWN
Classifier: Programming Language :: Python :: 3
Classifier: License :: OSI Approved :: MIT License
Classifier: Operating System :: OS Independent
Classifier: Intended Audience :: Developers
Classifier: Development Status :: 5 - Production/Stable
